osmnx/__init__.py
osmnx/_api.py
osmnx/_downloader.py
osmnx/_errors.py
osmnx/_nominatim.py
osmnx/_overpass.py
osmnx/_version.py
osmnx/bearing.py
osmnx/distance.py
osmnx/elevation.py
osmnx/features.py
osmnx/folium.py
osmnx/geocoder.py
osmnx/geometries.py
osmnx/graph.py
osmnx/io.py
osmnx/osm_xml.py
osmnx/plot.py
osmnx/projection.py
osmnx/routing.py
osmnx/settings.py
osmnx/simplification.py
osmnx/speed.py
osmnx/stats.py
osmnx/truncate.py
osmnx/utils.py
osmnx/utils_geo.py
osmnx/utils_graph.py
osmnx-1.7.0.dist-info/METADATA
osmnx-1.7.0.dist-info/WHEEL
osmnx-1.7.0.dist-info/licenses/LICENSE.txt
osmnx-1.7.0.dist-info/RECORD
