Metadata-Version: 2.1
Name: osmnx
Version: 1.7.0
Summary: Download, model, analyze, and visualize street networks and other geospatial features from OpenStreetMap
Project-URL: Documentation, https://osmnx.readthedocs.io
Project-URL: Repository, https://github.com/gboeing/osmnx
Author-email: Geoff Boeing <boeing@usc.edu>
Maintainer: OSMnx contributors
License: MIT License
License-File: LICENSE.txt
Keywords: GIS,Networks,OpenStreetMap,Routing
Classifier: Development Status :: 5 - Production/Stable
Classifier: Intended Audience :: Developers
Classifier: Intended Audience :: Science/Research
Classifier: License :: OSI Approved :: MIT License
Classifier: Operating System :: OS Independent
Classifier: Programming Language :: Python
Classifier: Programming Language :: Python :: 3
Classifier: Programming Language :: Python :: 3 :: Only
Classifier: Programming Language :: Python :: 3.8
Classifier: Programming Language :: Python :: 3.9
Classifier: Programming Language :: Python :: 3.10
Classifier: Programming Language :: Python :: 3.11
Classifier: Topic :: Scientific/Engineering :: GIS
Classifier: Topic :: Scientific/Engineering :: Information Analysis
Classifier: Topic :: Scientific/Engineering :: Mathematics
Classifier: Topic :: Scientific/Engineering :: Physics
Classifier: Topic :: Scientific/Engineering :: Visualization
Requires-Python: >=3.8
Requires-Dist: geopandas>=0.12
Requires-Dist: networkx>=2.5
Requires-Dist: numpy>=1.20
Requires-Dist: pandas>=1.1
Requires-Dist: requests>=2.27
Requires-Dist: shapely>=2.0
Provides-Extra: entropy
Requires-Dist: scipy>=1.5; extra == 'entropy'
Provides-Extra: neighbors
Requires-Dist: scikit-learn>=0.23; extra == 'neighbors'
Requires-Dist: scipy>=1.5; extra == 'neighbors'
Provides-Extra: raster
Requires-Dist: gdal; extra == 'raster'
Requires-Dist: rasterio>=1.3; extra == 'raster'
Provides-Extra: visualization
Requires-Dist: matplotlib>=3.5; extra == 'visualization'
